microeda/__init__.py
microeda/cli.py
microeda/core.py
microeda/report.py
microeda/viz.py
microeda-0.5.0.dist-info/licenses/LICENSE
microeda-0.5.0.dist-info/METADATA
microeda-0.5.0.dist-info/WHEEL
microeda-0.5.0.dist-info/entry_points.txt
microeda-0.5.0.dist-info/top_level.txt
microeda-0.5.0.dist-info/RECORD
