Metadata-Version: 2.4
Name: microeda
Version: 0.5.0
Summary: Ultra-lightweight micro EDA (exploratory data analysis) tool for small datasets
Author-email: Saptarshi Mondal <sammomondal659@gmail.com>
License-Expression: MIT
Project-URL: Homepage, https://github.com/SaptarshiMondal123/microeda
Keywords: eda,data analysis,statistics
Requires-Python: >=3.8
License-File: LICENSE
Requires-Dist: pandas>=1.5
Requires-Dist: numpy>=1.20
Requires-Dist: plotly>=5.20
Provides-Extra: rich
Requires-Dist: rich>=13.0; extra == "rich"
Provides-Extra: markdown
Requires-Dist: markdown>=3.4; extra == "markdown"
Dynamic: license-file
